{
    "platform_application": "false",
    "startup_configs": {
        "Config_3": {
            "machine_states": [
                
            ],
            "depends": {
                
            },
            "environments": [
                ""
            ],
            "scheduling_priority": "",
            "function_groups_states": {
                "": ""
            },
            "arguments": [
                ""
            ],
            "scheduling_policy": ""
        },
        "Config_1": {
            "machine_states": [
                
            ],
            "depends": {
                
            },
            "environments": [
                ""
            ],
            "scheduling_priority": "",
            "function_groups_states": {
                "": ""
            },
            "arguments": [
                ""
            ],
            "scheduling_policy": ""
        },
        "Config_2": {
            "machine_states": [
                
            ],
            "depends": {
                
            },
            "environments": [
                ""
            ],
            "scheduling_priority": "",
            "function_groups_states": {
                "": ""
            },
            "arguments": [
                ""
            ],
            "scheduling_policy": ""
        }
    }
}